mwinterest/__init__.py
mwinterest/mwcreate.py
mwinterest-1.0.0.dist-info/METADATA
mwinterest-1.0.0.dist-info/WHEEL
mwinterest-1.0.0.dist-info/top_level.txt
mwinterest-1.0.0.dist-info/RECORD
