Metadata-Version: 2.1
Name: mwinterest
Version: 1.0.0
Summary: MosoWong Interest Series
Home-page: UNKNOWN
Author: mosowong
Author-email: mosowong@163.com
License: GPLv3
Platform: UNKNOWN
Classifier: Programming Language :: Python :: 3
Classifier: License :: OSI Approved :: GNU General Public License v3 (GPLv3)
Classifier: Operating System :: OS Independent
Requires-Python: >=3.10.0
